[
    {
        "doctype": "Workflow Action Master",
        "name": "Propose",
        "workflow_action_name": "Propose"
    },
    {
        "doctype": "Workflow Action Master",
        "name": "Request Changes",
        "workflow_action_name": "Request Changes"
    },
    {
        "doctype": "Workflow Action Master",
        "name": "Approve",
        "workflow_action_name": "Approve"
    },
    {
        "doctype": "Workflow Action Master",
        "name": "Reject",
        "workflow_action_name": "Reject"
    },
    {
        "doctype": "Workflow Action Master",
        "name": "Reopen",
        "workflow_action_name": "Reopen"
    },
    {
        "doctype": "Workflow Action Master",
        "name": "Cancel",
        "workflow_action_name": "Cancel"
    }
]